Metadata-Version: 1.1
Name: perfume
Version: 0.2
Summary: Simple Object Oriented layer for Flask.
Home-page: http://github.com/hoh/perfume
Author: Hugo Herter
Author-email: hugoherter.com
License: BSD
Platform: UNKNOWN
Classifier: Intended Audience :: Developers
Classifier: Environment :: Web Environment
Classifier: Development Status :: 3 - Alpha
Classifier: Natural Language :: English
Classifier: License :: OSI Approved
Classifier: Operating System :: OS Independent
Classifier: Programming Language :: Python
Classifier: Programming Language :: Python :: 2.5
Classifier: Programming Language :: Python :: 2.6
Classifier: Programming Language :: Python :: 2.7
Classifier: Topic :: Internet :: WWW/HTTP :: Dynamic Content
Classifier: Topic :: Software Development :: Libraries :: Python Modules
